pystructs/__init__.py
pystructs/abc.py
pystructs/net.py
pystructs/py.typed
pystructs/std.py
pystructs/struct.py
pystructs/tests/__init__.py
pystructs/tests/net.py
pystructs/tests/std.py
pystructs/tests/struct.py
pystructs3-0.0.8.dist-info/LICENSE
pystructs3-0.0.8.dist-info/METADATA
pystructs3-0.0.8.dist-info/WHEEL
pystructs3-0.0.8.dist-info/top_level.txt
pystructs3-0.0.8.dist-info/RECORD
